redenv/__init__.py
redenv/client.py
redenv/crypto.py
redenv/errors.py
redenv/expand.py
redenv/py.typed
redenv/secrets.py
redenv/types.py
redenv/utils.py
redenv/sync/__init__.py
redenv/sync/client.py
redenv/sync/utils.py
redenv-0.3.0.dist-info/METADATA
redenv-0.3.0.dist-info/WHEEL
redenv-0.3.0.dist-info/licenses/LICENSE
redenv-0.3.0.dist-info/RECORD
