Metadata-Version: 2.4
Name: redenv
Version: 0.3.0
Summary: A zero-knowledge, end-to-end encrypted secret management SDK for Python.
Project-URL: Homepage, https://github.com/redenv-labs/redenv
Project-URL: Documentation, https://github.com/redenv-labs/redenv/tree/main/packages/python-client
Project-URL: Repository, https://github.com/redenv-labs/redenv
Project-URL: Issues, https://github.com/redenv-labs/redenv/issues
Author-email: PRAS <prassamin@gmail.com>
License: MIT License
License-File: LICENSE
Keywords: dotenv,encryption,redis,sdk,secrets,security,upstash
Classifier: Development Status :: 4 - Beta
Classifier: Intended Audience :: Developers
Classifier: License :: OSI Approved :: MIT License
Classifier: Operating System :: OS Independent
Classifier: Programming Language :: Python :: 3
Classifier: Programming Language :: Python :: 3.8
Classifier: Programming Language :: Python :: 3.9
Classifier: Programming Language :: Python :: 3.10
Classifier: Programming Language :: Python :: 3.11
Classifier: Programming Language :: Python :: 3.12
Classifier: Topic :: Security
Classifier: Topic :: Software Development :: Libraries :: Python Modules
Requires-Python: >=3.8
Requires-Dist: cachetools>=5.0.0
Requires-Dist: cryptography>=41.0.0
Requires-Dist: upstash-redis>=1.0.0
Provides-Extra: dev
Requires-Dist: build; extra == 'dev'
Requires-Dist: pyright; extra == 'dev'
Requires-Dist: pytest; extra == 'dev'
Requires-Dist: pytest-asyncio; extra == 'dev'
Requires-Dist: python-dotenv; extra == 'dev'
Requires-Dist: ruff; extra == 'dev'
Requires-Dist: twine; extra == 'dev'
